{
  "default": "tensor_basics",
  "examples": [
    { "id": "tensor_basics", "label": "Tensor Basics + CUDA Info", "file": "examples/tensor_basics.py" },
    { "id": "matmul_relu", "label": "Matmul + ReLU", "file": "examples/matmul_relu.py" },
    { "id": "reshape_transpose", "label": "Reshape + Transpose", "file": "examples/reshape_transpose.py" },
    { "id": "rand_tensor", "label": "Random Tensor (rand)", "file": "examples/rand_tensor.py" },
    { "id": "clamp_values", "label": "Clamp Values", "file": "examples/clamp_values.py" },
    { "id": "where_select", "label": "Where Selection", "file": "examples/where_select.py" },
    { "id": "argmax_argmin", "label": "Argmax + Argmin", "file": "examples/argmax_argmin.py" },
    { "id": "randn_tensor", "label": "Random Normal (randn)", "file": "examples/randn_tensor.py" },
    { "id": "arange_int32", "label": "Arange Int32", "file": "examples/arange_int32.py" },
    { "id": "full_and_full_like", "label": "Full + Full Like", "file": "examples/full_and_full_like.py" },
    { "id": "unary_abs_neg", "label": "Unary Abs + Neg", "file": "examples/unary_abs_neg.py" },
    { "id": "unary_sqrt_exp_log", "label": "Unary Sqrt + Exp + Log", "file": "examples/unary_sqrt_exp_log.py" },
    { "id": "shape_flatten_squeeze", "label": "Shape Flatten + Squeeze", "file": "examples/shape_flatten_squeeze.py" },
    { "id": "shape_transpose_permute", "label": "Shape Transpose + Permute", "file": "examples/shape_transpose_permute.py" },
    { "id": "index_select_slice", "label": "Index Select + Slice", "file": "examples/index_select_slice.py" },
    { "id": "cat_stack", "label": "Cat + Stack", "file": "examples/cat_stack.py" },
    { "id": "expand_index_select", "label": "Expand + Index Select", "file": "examples/expand_index_select.py" },
    { "id": "broadcasting", "label": "Broadcasting", "file": "examples/broadcasting.py" },
    { "id": "compare_ops", "label": "Compare Ops", "file": "examples/compare_ops.py" },
    { "id": "unary_advanced", "label": "Unary Advanced (sigmoid, tanh, gelu...)", "file": "examples/unary_advanced.py" },
    { "id": "reduce_dim", "label": "Reduction by dim", "file": "examples/reduce_dim.py" },
    { "id": "masked_select_fill", "label": "Masked Select + Fill", "file": "examples/masked_select_fill.py" },
    { "id": "broadcast_compare", "label": "Broadcast + Compare", "file": "examples/broadcast_compare.py" },
    { "id": "reduce_dim_keepdim", "label": "Reduction keepdim", "file": "examples/reduce_dim_keepdim.py" },
    { "id": "nn_linear_relu", "label": "nn Linear + ReLU", "file": "examples/nn_linear_relu.py" },
    { "id": "nn_conv2d", "label": "nn Conv2d", "file": "examples/nn_conv2d.py" },
    { "id": "nn_batchnorm", "label": "nn BatchNorm1d", "file": "examples/nn_batchnorm.py" },
    { "id": "nn_pooling", "label": "nn MaxPool2d + AvgPool2d", "file": "examples/nn_pooling.py" },
    { "id": "nn_losses", "label": "nn Losses", "file": "examples/nn_losses.py" }
  ]
}
